Metadata-Version: 2.4
Name: large-image-tasks
Version: 1.34.0
Summary: Girder Worker tasks for Large Image.
Author: Kitware Inc
Author-email: kitware@kitware.com
License: Apache-2.0
Classifier: Development Status :: 5 - Production/Stable
Classifier: Topic :: Scientific/Engineering
Classifier: Intended Audience :: Science/Research
Classifier: Programming Language :: Python :: 3
Classifier: Programming Language :: Python :: 3.10
Classifier: Programming Language :: Python :: 3.11
Classifier: Programming Language :: Python :: 3.12
Classifier: Programming Language :: Python :: 3.13
Classifier: Programming Language :: Python :: 3.14
Requires-Python: >=3.10
License-File: LICENSE
Requires-Dist: girder-worker-utils>=0.8.5
Provides-Extra: girder
Requires-Dist: large-image-converter>=1.34.0; extra == "girder"
Requires-Dist: girder-worker[girder]>=0.6.0; extra == "girder"
Provides-Extra: worker
Requires-Dist: large-image-converter[sources]>=1.34.0; extra == "worker"
Requires-Dist: girder-worker[worker]>=0.6.0; extra == "worker"
Dynamic: author
Dynamic: author-email
Dynamic: classifier
Dynamic: description
Dynamic: description-content-type
Dynamic: license
Dynamic: license-file
Dynamic: provides-extra
Dynamic: requires-dist
Dynamic: requires-python
Dynamic: summary
